Metadata-Version: 2.1
Name: nekoimg
Version: 0.7
Summary: This shows you a random neko image
Home-page: https://github.com/Cl1ckerr/nekoimg
Author: Cl1cker
Author-email: tji85047@gmail.com
License: MIT
Download-URL: https://github.com/Cl1ckerr/nekoimg/tarball/0.4
Keywords: webbrowser,random,neko
Platform: UNKNOWN
